AreaCalcF/__init__.py
AreaCalcF/area.py
PythonProject/__init__.py
PythonProject/area.py
AreaCalcF-0.0.7.dist-info/METADATA
AreaCalcF-0.0.7.dist-info/WHEEL
AreaCalcF-0.0.7.dist-info/top_level.txt
AreaCalcF-0.0.7.dist-info/RECORD
