Metadata-Version: 2.1
Name: AreaCalcF
Version: 0.0.7
Summary: This is the simplest module for calculation square of input figure.
Home-page: http://wubbalubba/area_function
Author: fominaav
Author-email: fomina.av@phystech.edu
Project-URL: GitHub, https://github.com/vvubbalubbab
Keywords: files speedfiles
Classifier: Programming Language :: Python :: 3.11
Classifier: License :: OSI Approved :: MIT License
Classifier: Operating System :: OS Independent
Requires-Python: >=3.6
Requires-Dist: requests>=2.25.1
